random_vinkesh_ti/__init__.py
random_vinkesh_ti/api_client.py
random_vinkesh_ti/api_response.py
random_vinkesh_ti/configuration.py
random_vinkesh_ti/exceptions.py
random_vinkesh_ti/py.typed
random_vinkesh_ti/rest.py
random_vinkesh_ti/api/__init__.py
random_vinkesh_ti/api/pet_api.py
random_vinkesh_ti/api/store_api.py
random_vinkesh_ti/api/user_api.py
random_vinkesh_ti/models/__init__.py
random_vinkesh_ti/models/address.py
random_vinkesh_ti/models/api_response.py
random_vinkesh_ti/models/category.py
random_vinkesh_ti/models/customer.py
random_vinkesh_ti/models/order.py
random_vinkesh_ti/models/pet.py
random_vinkesh_ti/models/tag.py
random_vinkesh_ti/models/user.py
random_vinkesh_ti-0.0.1.dist-info/METADATA
random_vinkesh_ti-0.0.1.dist-info/WHEEL
random_vinkesh_ti-0.0.1.dist-info/top_level.txt
random_vinkesh_ti-0.0.1.dist-info/RECORD
